Workbook

Sheet Summary
A1: NINJA VAN
A2: Sales and stock report · Kahf
A4: Period | B4: October 2026 (1 to 31 October)
A5: Hubs | B5: MA5 Cawang, KJ5 Kemanggisan
A6: Reference | B6: RPT-KHF-2610
A7: Made | B7: 04/11/2026 10:00 WIB
A9: Figure | B9: MA5 | C9: KJ5 | D9: Total
A10: Units sold | B10: =SUMIFS('Sales by SKU'!$G$8:$G$35,'Sales by SKU'!$A$8:$A$35,"MA5") | C10: =SUMIFS('Sales by SKU'!$G$8:$G$35,'Sales by SKU'!$A$8:$A$35,"KJ5") | D10: =B10+C10
A11: Sales value (Rp, Grab menu price) | B11: =SUMIFS('Sales by SKU'!$H$8:$H$35,'Sales by SKU'!$A$8:$A$35,"MA5") | C11: =SUMIFS('Sales by SKU'!$H$8:$H$35,'Sales by SKU'!$A$8:$A$35,"KJ5") | D11: =B11+C11
A12: Orders | B12: =ROUND(B10/1.6,0) | C12: =ROUND(C10/1.6,0) | D12: =B12+C12
A13: Orders cancelled: item out of stock | B13: 2 | C13: 1 | D13: =B13+C13
A14: Stock at end (units) | B14: =SUMIFS('Sales by SKU'!$I$8:$I$35,'Sales by SKU'!$A$8:$A$35,"MA5") | C14: =SUMIFS('Sales by SKU'!$I$8:$I$35,'Sales by SKU'!$A$8:$A$35,"KJ5") | D14: =B14+C14
A15: Units per order | B15: =IFERROR(B10/B12,0) | C15: =IFERROR(C10/C12,0) | D15: =IFERROR(D10/D12,0)
A16: Cancelled for out of stock, % of orders | B16: =IFERROR(B13/B12,0) | C16: =IFERROR(C13/C12,0) | D16: =IFERROR(D13/D12,0)
A18: Sales value = Grab menu price on the day of the order × units, before Grab commission and promotions. Cancelled orders are not counted.
A19: A pack of 2 counts as 2 units of its product.

Sheet Sales by SKU
A1: NINJA VAN
A2: Sales by SKU · Kahf
A4: Period | B4: October 2026 (1 to 31 October)
A5: Weeks in period | B5: 4.43
A7: Hub | B7: SKU code | C7: Barcode | D7: Product | E7: Size | F7: Menu price (Rp) | G7: Units sold | H7: Sales value (Rp) | I7: Stock at end | J7: Average sold per week | K7: Weeks of cover | L7: Notes
A8: MA5 | B8: KHF-0001 | C8: 8993137710428 | D8: Kahf Oil and Acne Care Face Wash | E8: 100 ml | F8: 43900 | G8: 28 | H8: =F8*G8 | I8: 14 | J8: =G8/$B$5 | K8: =IFERROR(I8/J8,"-")
A9: MA5 | B9: KHF-0002 | C9: 8993137740838 | D9: Kahf Oil and Acne Care Face Wash | E9: 50 ml | F9: 29000 | G9: 30 | H9: =F9*G9 | I9: 5 | J9: =G9/$B$5 | K9: =IFERROR(I9/J9,"-")
A10: MA5 | B10: KHF-0003 | C10: 8993137710411 | D10: Kahf Skin Energizing and Brightening Face Wash | E10: 100 ml | F10: 42500 | G10: 31 | H10: =F10*G10 | I10: 13 | J10: =G10/$B$5 | K10: =IFERROR(I10/J10,"-")
A11: MA5 | B11: KHF-0004 | C11: 8993137740845 | D11: Kahf Skin Energizing and Brightening Face Wash (Bright Foam) | E11: 50 ml | F11: 29000 | G11: 21 | H11: =F11*G11 | I11: 12 | J11: =G11/$B$5 | K11: =IFERROR(I11/J11,"-")
A12: MA5 | B12: KHF-0005 | C12: 8993137713634 | D12: Kahf Brightening and Dark Spot Scrub Face Wash | E12: 100 ml | F12: 42500 | G12: 25 | H12: =F12*G12 | I12: 7 | J12: =G12/$B$5 | K12: =IFERROR(I12/J12,"-")
A13: MA5 | B13: KHF-0006 | C13: 8993137008471 | D13: Kahf Acne and Pore Cleanse Scrub Face Wash | E13: 100 ml | F13: 42500 | G13: 28 | H13: =F13*G13 | I13: 7 | J13: =G13/$B$5 | K13: =IFERROR(I13/J13,"-")
A14: MA5 | B14: KHF-0007 | C14: 8993137723756 | D14: Kahf Triple Action Oil and Comedo Defense Face Wash | E14: 100 ml | F14: 52800 | G14: 29 | H14: =F14*G14 | I14: 7 | J14: =G14/$B$5 | K14: =IFERROR(I14/J14,"-")
A15: MA5 | B15: KHF-0008 | C15: 8993137015523 | D15: Kahf Acne Care AminoGel Face Wash | E15: 100 ml | F15: 0 | G15: 34 | H15: =F15*G15 | I15: 15 | J15: =G15/$B$5 | K15: =IFERROR(I15/J15,"-")
A16: MA5 | B16: KHF-0009 | C16: none yet | D16: Kahf Acne Care AminoGel Face Wash (travel size) | E16: 50 ml | F16: 27500 | G16: 25 | H16: =F16*G16 | I16: 12 | J16: =G16/$B$5 | K16: =IFERROR(I16/J16,"-")
A17: MA5 | B17: KHF-0010 | C17: 8993137015530 | D17: Kahf Bright Revitalizing AminoGel Face Wash | E17: 100 ml | F17: 47500 | G17: 28 | H17: =F17*G17 | I17: 14 | J17: =G17/$B$5 | K17: =IFERROR(I17/J17,"-")
A18: MA5 | B18: KHF-0011 | C18: none yet | D18: Kahf Bright Revitalizing AminoGel Face Wash (travel size) | E18: 50 ml | F18: 27500 | G18: 30 | H18: =F18*G18 | I18: 5 | J18: =G18/$B$5 | K18: =IFERROR(I18/J18,"-")
A19: MA5 | B19: KHF-0013 | C19: 8993137729765 | D19: Kahf Face Spray All-in-One and Power Toning (pump mist) | E19: 100 ml | F19: 43000 | G19: 21 | H19: =F19*G19 | I19: 12 | J19: =G19/$B$5 | K19: =IFERROR(I19/J19,"-")
... A35: KJ5 | B35: KHF-0015 | C35: none yet | D35: Kahf Acne Clear & Post-acne Repair Niosome Serum | E35: 25 ml | F35: 100000 | G35: 17 | H35: =F35*G35 | I35: 10 | J35: =G35/$B$5 | K35: =IFERROR(I35/J35,"-")
A36: Total | G36: =SUM(G8:G35) | H36: =SUM(H8:H35) | I36: =SUM(I8:I35)

Sheet Stock and deliveries
A1: NINJA VAN
A2: Stock reconciliation · Kahf
A4: Period | B4: October 2026 (1 to 31 October)
A6: Hub | B6: Opening stock | C6: Received | D6: Sold | E6: Returned to brand | F6: Written off | G6: Expected | H6: Counted at month end | I6: Difference
A7: MA5 | B7: 140 | C7: 386 | D7: =SUMIFS('Sales by SKU'!$G$8:$G$35,'Sales by SKU'!$A$8:$A$35,"MA5") | E7: 3 | F7: 2 | G7: =B7+C7-D7-E7-F7 | H7: 137 | I7: =H7-G7
A8: KJ5 | B8: 110 | C8: 282 | D8: =SUMIFS('Sales by SKU'!$G$8:$G$35,'Sales by SKU'!$A$8:$A$35,"KJ5") | E8: 1 | F8: 1 | G8: =B8+C8-D8-E8-F8 | H8: 166 | I8: =H8-G8
A10: Deliveries received
A11: AWB | B11: Date | C11: Hub | D11: Requested (PO) | E11: Sent (Surat Jalan) | F11: Received | G11: Difference | H11: PO number
A12: JX2610010231 | B12: 03/10/2026 | C12: MA5 | D12: 96 | E12: 96 | F12: 96 | G12: =F12-E12 | H12: RPL-MA5-2609-03
A13: JX2610010877 | B13: 10/10/2026 | C13: KJ5 | D13: 72 | E13: 70 | F13: 70 | G13: =F13-E13 | H13: RPL-KJ5-2610-01
A14: JX2610011502 | B14: 17/10/2026 | C14: MA5 | D14: 84 | E14: 84 | F14: 86 | G14: =F14-E14 | H14: RPL-MA5-2610-02
A16: Returns and write-offs
A17: Hub | B17: SKU code | C17: Reason | D17: Units | E17: Cost borne by | F17: Date
A18: MA5 | B18: KHF-0006 | C18: Damaged in the hub | D18: 1 | E18: Ninja | F18: 12/10/2026
A19: MA5 | B19: KHF-0013 | C19: Faulty pack (leak) | D19: 1 | E19: Brand | F19: 20/10/2026
A20: MA5 | B20: KHF-0014 | C20: Returned: expiry near | D20: 3 | E20: Brand | F20: 28/10/2026
A21: KJ5 | B21: KHF-0003 | C21: Faulty pack (leak) | D21: 1 | E21: Brand | F21: 22/10/2026
